sayan_pack/_init_.py
sayan_pack/sayan_pack.py
sayan_pack-1.0.dist-info/License.txt
sayan_pack-1.0.dist-info/METADATA
sayan_pack-1.0.dist-info/WHEEL
sayan_pack-1.0.dist-info/top_level.txt
sayan_pack-1.0.dist-info/RECORD
