Metadata-Version: 2.1
Name: sayan-pack
Version: 1.0
Summary: Regular
Home-page: UNKNOWN
Author: Osayanhu Imoisili
Author-email: jerryosaimo@gmail.com
License: UNKNOWN
Platform: UNKNOWN
